autosync/__init__.py
autosync/_metadata.py
autosync/const.py
autosync/main.py
autosync/cli/__init__.py
autosync/cli/cli.py
autosync/cli/commands/__init__.py
autosync/cli/commands/cmd_config.py
autosync/cli/commands/cmd_export.py
autosync/cli/commands/cmd_sync.py
autosync/lib/__init__.py
autosync/lib/bcolors.py
autosync/lib/cache.py
autosync/lib/find.py
autosync/lib/helpers.py
autosync/lib/merakiapi.py
autosync/lib/netcompare.py
autosync/mnetutils/__init__.py
autosync/mnetutils/clone.py
autosync/mnetutils/resync.py
autosync/mnetutils/sync.py
autosync/mnetutils/test_wireless.py
autosync/model/__init__.py
autosync/model/appconfig.py
autosync/model/meraki.py
autosync/model/mnet.py
autosync/model/orgs.py
autosync/model/overrides.py
autosync/products/__init__.py
autosync/products/networks.py
autosync/products/switch.py
autosync/products/wireless.py
autosync/utils/__init__.py
autosync/utils/_getorginizations.py
autosync/utils/_orgsyncprocessor.py
autosync/utils/_validateorginization.py
autosync/utils/processor.py
Meraki_Auto_Sync-1.190.dist-info/LICENSE.txt
Meraki_Auto_Sync-1.190.dist-info/METADATA
Meraki_Auto_Sync-1.190.dist-info/WHEEL
Meraki_Auto_Sync-1.190.dist-info/entry_points.txt
Meraki_Auto_Sync-1.190.dist-info/top_level.txt
Meraki_Auto_Sync-1.190.dist-info/RECORD
