Metadata-Version: 2.1
Name: Meraki-Auto-Sync
Version: 1.190
Summary: CLI Tool To Sync Meraki Network Accross Orginizations based on Tags
Home-page: UNKNOWN
Author: Josh Lipton
Author-email: joliptn@cisco.com
License: UNKNOWN
Platform: UNKNOWN
Requires-Dist: aiohttp
Requires-Dist: async-timeout
Requires-Dist: attrs
Requires-Dist: bcolors
Requires-Dist: certifi
Requires-Dist: chardet
Requires-Dist: idna
Requires-Dist: meraki
Requires-Dist: multidict
Requires-Dist: requests
Requires-Dist: typing-extensions
Requires-Dist: urllib3
Requires-Dist: yarl
Requires-Dist: http3
Requires-Dist: click
Requires-Dist: pandas
Requires-Dist: tabulate
Requires-Dist: python-dateutil
Requires-Dist: automodinit
Requires-Dist: python-dotenv
Requires-Dist: wheel
Requires-Dist: deepdiff
Requires-Dist: jsonpickle
